setup.py
autoimp/__init__.py
autoimp.egg-info/PKG-INFO
autoimp.egg-info/SOURCES.txt
autoimp.egg-info/dependency_links.txt
autoimp.egg-info/top_level.txt