Metadata-Version: 1.1
Name: autoimp
Version: 1.0.4
Summary: Automatic Python imports
Home-page: https://github.com/connellybarnes/autoimp
Author: Connelly Barnes
Author-email: connellybarnes at yahoo.com
License: MIT
Keywords: interactive interpreter development imports convenience
Platform: UNKNOWN
Classifier: Development Status :: 5 - Production/Stable
Classifier: Intended Audience :: Developers
Classifier: Topic :: Software Development :: Build Tools
Classifier: License :: OSI Approved :: MIT License
Classifier: Programming Language :: Python :: 2
Classifier: Programming Language :: Python :: 2.6
Classifier: Programming Language :: Python :: 2.7
Classifier: Programming Language :: Python :: 3
Classifier: Programming Language :: Python :: 3.2
Classifier: Programming Language :: Python :: 3.3
Classifier: Programming Language :: Python :: 3.4
